{"objects":[{"id":187,"nombre":"Almolonga"},{"id":188,"nombre":"Cabricán"},{"id":195,"nombre":"Flores Costa Cuca"},{"id":190,"nombre":"Cantel"},{"id":192,"nombre":"Colomba Costa Cuca"},{"id":193,"nombre":"Concepción Chiquirichapa"},{"id":194,"nombre":"El Palmar"},{"id":196,"nombre":"Génova"},{"id":197,"nombre":"Huitán"},{"id":191,"nombre":"Coatepeque"},{"id":1,"nombre":"Quetzaltenango"},{"id":4,"nombre":"La Esperanza"},{"id":198,"nombre":"Palestina de Los Altos"},{"id":16,"nombre":"Olintepeque"},{"id":199,"nombre":"Salcajá"},{"id":200,"nombre":"San Carlos Sija"},{"id":201,"nombre":"San Francisco La Unión"},{"id":202,"nombre":"San Juan Ostuncalco"},{"id":203,"nombre":"San Martín Sacatepéquez"},{"id":204,"nombre":"San Mateo"}]}
