{"objects": [{"direccion": "Zona 20", "id": 4120}, {"direccion": "Zona 19", "id": 4119}, {"direccion": "Zona 18", "id": 4118}, {"direccion": "Zona 17", "id": 4117}, {"direccion": "Zona 16", "id": 4116}, {"direccion": "Zona 15", "id": 4115}, {"direccion": "Zona 14", "id": 4114}, {"direccion": "Zona 13", "id": 4113}, {"direccion": "Zona 12", "id": 4112}, {"direccion": "Zona 11", "id": 4111}, {"direccion": "Zona 10", "id": 4110}, {"direccion": "Zona 9", "id": 4109}, {"direccion": "Zona 8", "id": 4108}, {"direccion": "Zona 7", "id": 4107}, {"direccion": "Zona 6", "id": 4106}, {"direccion": "Zona 5", "id": 4105}, {"direccion": "Zona 4", "id": 4104}, {"direccion": "Zona 3", "id": 4103}, {"direccion": "Zona 2", "id": 4102}, {"direccion": "Zona 1", "id": 4101}]}