{"objects": [{"direccion": "Zona 20", "id": 1260}, {"direccion": "Zona 19", "id": 1259}, {"direccion": "Zona 18", "id": 1258}, {"direccion": "Zona 17", "id": 1257}, {"direccion": "Zona 16", "id": 1256}, {"direccion": "Zona 15", "id": 1255}, {"direccion": "Zona 14", "id": 1254}, {"direccion": "Zona 13", "id": 1253}, {"direccion": "Zona 12", "id": 1252}, {"direccion": "Zona 11", "id": 1251}, {"direccion": "Zona 10", "id": 1250}, {"direccion": "Zona 9", "id": 1249}, {"direccion": "Zona 8", "id": 1248}, {"direccion": "Zona 7", "id": 1247}, {"direccion": "Zona 6", "id": 1246}, {"direccion": "Zona 5", "id": 1245}, {"direccion": "Zona 4", "id": 1244}, {"direccion": "Zona 3", "id": 1243}, {"direccion": "Zona 2", "id": 1242}, {"direccion": "Zona 1", "id": 1241}]}